moganclient/__init__.py
moganclient/common/__init__.py
moganclient/common/base.py
moganclient/common/exceptions.py
moganclient/common/http.py
moganclient/common/i18n.py
moganclient/common/utils.py
moganclient/osc/__init__.py
moganclient/osc/plugin.py
moganclient/osc/v1/__init__.py
moganclient/osc/v1/aggregate.py
moganclient/osc/v1/availability_zone.py
moganclient/osc/v1/flavor.py
moganclient/osc/v1/keypair.py
moganclient/osc/v1/manageable_server.py
moganclient/osc/v1/node.py
moganclient/osc/v1/server.py
moganclient/osc/v1/server_group.py
moganclient/tests/__init__.py
moganclient/tests/functional/__init__.py
moganclient/tests/functional/base.py
moganclient/tests/unit/__init__.py
moganclient/tests/unit/base.py
moganclient/tests/unit/fakes.py
moganclient/tests/unit/common/__init__.py
moganclient/tests/unit/common/test_base.py
moganclient/tests/unit/common/test_exceptions.py
moganclient/tests/unit/common/test_http.py
moganclient/tests/unit/common/test_utils.py
moganclient/tests/unit/osc/__init__.py
moganclient/tests/unit/osc/test_plugin.py
moganclient/tests/unit/osc/v1/__init__.py
moganclient/tests/unit/osc/v1/test_aggregate.py
moganclient/tests/unit/osc/v1/test_availability_zone.py
moganclient/tests/unit/osc/v1/test_flavor.py
moganclient/tests/unit/osc/v1/test_manageable_server.py
moganclient/tests/unit/osc/v1/test_node.py
moganclient/tests/unit/osc/v1/test_server.py
moganclient/tests/unit/osc/v1/test_server_group.py
moganclient/v1/__init__.py
moganclient/v1/aggregate.py
moganclient/v1/availability_zone.py
moganclient/v1/client.py
moganclient/v1/flavor.py
moganclient/v1/keypair.py
moganclient/v1/manageable_server.py
moganclient/v1/node.py
moganclient/v1/server.py
moganclient/v1/server_group.py
python_moganclient-0.1.0.dist-info/DESCRIPTION.rst
python_moganclient-0.1.0.dist-info/METADATA
python_moganclient-0.1.0.dist-info/RECORD
python_moganclient-0.1.0.dist-info/WHEEL
python_moganclient-0.1.0.dist-info/entry_points.txt
python_moganclient-0.1.0.dist-info/metadata.json
python_moganclient-0.1.0.dist-info/pbr.json
python_moganclient-0.1.0.dist-info/top_level.txt
