Metadata-Version: 2.0
Name: python-moganclient
Version: 0.1.0
Summary: Python client library for OpenStack Mogan project.
Home-page: http://www.openstack.org/
Author: OpenStack
Author-email: openstack-dev@lists.openstack.org
License: Apache License, Version 2.0
Platform: UNKNOWN
Classifier: Development Status :: 5 - Production/Stable
Classifier: Environment :: Console
Classifier: Environment :: OpenStack
Classifier: Intended Audience :: Information Technology
Classifier: Intended Audience :: System Administrators
Classifier: License :: OSI Approved :: Apache Software License
Classifier: Operating System :: POSIX :: Linux
Classifier: Programming Language :: Python
Classifier: Programming Language :: Python :: 2
Classifier: Programming Language :: Python :: 2.7
Classifier: Programming Language :: Python :: 3
Classifier: Programming Language :: Python :: 3.5
Requires-Dist: keystoneauth1 (>=3.2.0)
Requires-Dist: osc-lib (>=1.7.0)
Requires-Dist: oslo.i18n (>=3.15.3)
Requires-Dist: oslo.serialization (!=2.19.1,>=2.18.0)
Requires-Dist: oslo.utils (>=3.28.0)
Requires-Dist: pbr (!=2.1.0,>=2.0.0)
Requires-Dist: requests (>=2.14.2)
Requires-Dist: six (>=1.9.0)
